filter_vcf/__init__.py
filter_vcf/process.py
filter_vcf/util/__init__.py
filter_vcf/util/addDepth.py
filter_vcf/util/checkArgs.py
filter_vcf/util/cleanAD.py
filter_vcf/util/cleanGT.py
filter_vcf/util/convertChrName.py
filter_vcf/util/decompose.py
filter_vcf/util/detectVcf.py
filter_vcf/util/execSubprocess.py
filter_vcf/util/filterCarisLiquid.py
filter_vcf/util/filterContigs.py
filter_vcf/util/lineNormalization.py
filter_vcf/util/normalize.py
filter_vcf/util/removeNonRef.py
filter_vcf/util/sortVcf.py
filter_vcf/util/unique.py
filter_vcf/util/userFilter.py
filter_vcf-0.2.9.dist-info/WHEEL
filter_vcf-0.2.9.dist-info/METADATA
filter_vcf-0.2.9.dist-info/RECORD
