Metadata-Version: 2.1
Name: filter-vcf
Version: 0.2.9
Summary: LifeOmic VCF filtering
License: MIT
Author-email: LifeOmic Development <development@lifeomic.com>
Requires-Python: >=3.9
Requires-Dist: fastnumbers>=5.0.1
Requires-Dist: lifeomic-logging==0.3.2
Requires-Dist: natsort>=8.3.1
Requires-Dist: setuptools>=67.6.1
